autofaq/__init__.py
autofaq/clean/__init__.py
autofaq/clean/classic.py
autofaq/clean/cleaner.py
autofaq/clean/entailment.py
autofaq/clean/fuzzy_match.py
autofaq/clean/page.py
autofaq/clean/subject.py
autofaq/cli/__init__.py
autofaq/cli/entry.py
autofaq/cli/commands/__init__.py
autofaq/cli/commands/clean.py
autofaq/cli/commands/embed.py
autofaq/cli/commands/extract.py
autofaq/cli/commands/init.py
autofaq/cli/commands/keywords.py
autofaq/cli/commands/render.py
autofaq/cli/commands/search.py
autofaq/config/__init__.py
autofaq/config/binder.py
autofaq/config/configurable.py
autofaq/extract/__init__.py
autofaq/extract/better_extractor.py
autofaq/extract/easy_extractor.py
autofaq/extract/extractor.py
autofaq/language_model/__init__.py
autofaq/language_model/embedder.py
autofaq/language_model/xlm.py
autofaq/language_model/xlm_embedder.py
autofaq/render/__init__.py
autofaq/render/json_renderer.py
autofaq/render/md_renderer.py
autofaq/render/renderer.py
autofaq/util/__init__.py
autofaq/util/dir.py
autofaq/util/hash.py
autofaq/util/out.py
auto_faq-0.4.1.dist-info/LICENSE
auto_faq-0.4.1.dist-info/METADATA
auto_faq-0.4.1.dist-info/WHEEL
auto_faq-0.4.1.dist-info/entry_points.txt
auto_faq-0.4.1.dist-info/top_level.txt
auto_faq-0.4.1.dist-info/RECORD
