Metadata-Version: 2.1
Name: auto-faq
Version: 0.4.1
Summary: Automatic FAQ Mining Framework
Home-page: https://github.com/AminRezaei0x443/auto-faq
Author: Amin Rezaei
Author-email: AminRezaei0x443@gmail.com
License: MIT
License-File: LICENSE
